qudix/__init__.py
qudix/app.py
qudix-0.1.10.dist-info/licenses/LICENSE
qudix-0.1.10.dist-info/licenses/LICENSE-APACHE
qudix-0.1.10.dist-info/licenses/LICENSE-MIT
qudix-0.1.10.dist-info/licenses/NOTICE
qudix-0.1.10.dist-info/METADATA
qudix-0.1.10.dist-info/WHEEL
qudix-0.1.10.dist-info/entry_points.txt
qudix-0.1.10.dist-info/top_level.txt
qudix-0.1.10.dist-info/RECORD
