Metadata-Version: 2.4
Name: qudix
Version: 0.1.10
Summary: Terminal-based text editor with mouse-driven toolbar actions.
Author: Sahil Pethe
License: Apache-2.0 OR MIT
Requires-Python: >=3.11
License-File: LICENSE
License-File: LICENSE-APACHE
License-File: LICENSE-MIT
License-File: NOTICE
Requires-Dist: prompt_toolkit<3.1,>=3.0.43
Provides-Extra: release
Requires-Dist: build>=1; extra == "release"
Requires-Dist: twine>=4; extra == "release"
Requires-Dist: wheel>=0.41; extra == "release"
Dynamic: license-file
